setup.py
transpose/__init__.py
transpose/converters.py
transpose/schema.py
transpose.egg-info/PKG-INFO
transpose.egg-info/SOURCES.txt
transpose.egg-info/dependency_links.txt
transpose.egg-info/entry_points.txt
transpose.egg-info/namespace_packages.txt
transpose.egg-info/not-zip-safe
transpose.egg-info/requires.txt
transpose.egg-info/top_level.txt