Metadata-Version: 1.1
Name: transpose
Version: 0.0.3
Summary: detect jsonschema in data and transpose into other formats
Home-page: http://github.com/abelsonlive/transpose
Author: Brian Abelson
Author-email: brianabelson@gmail.com
License: MIT
Platform: UNKNOWN
Classifier: Development Status :: 3 - Alpha
Classifier: Intended Audience :: Developers
Classifier: License :: OSI Approved :: MIT License
Classifier: Operating System :: OS Independent
Classifier: Programming Language :: Python
